orangengine/__init__.py
orangengine/dispatcher.py
orangengine/utils.py
orangengine/drivers/__init__.py
orangengine/drivers/_juniper_utils.py
orangengine/drivers/base.py
orangengine/drivers/juniper_srx.py
orangengine/drivers/palo_alto_base.py
orangengine/drivers/palo_alto_panorama.py
orangengine/errors/__init__.py
orangengine/errors/errors.py
orangengine/models/__init__.py
orangengine/models/base/__init__.py
orangengine/models/base/baseaddress.py
orangengine/models/base/baseaddressgroup.py
orangengine/models/base/baseobject.py
orangengine/models/base/basepolicy.py
orangengine/models/base/baseservice.py
orangengine/models/base/baseservicegroup.py
orangengine/models/juniper/__init__.py
orangengine/models/juniper/address.py
orangengine/models/juniper/addressgroup.py
orangengine/models/juniper/policy.py
orangengine/models/juniper/service.py
orangengine/models/juniper/servicegroup.py
orangengine/models/paloalto/__init__.py
orangengine/models/paloalto/address.py
orangengine/models/paloalto/addressgroup.py
orangengine/models/paloalto/applciation.py
orangengine/models/paloalto/applicationgroup.py
orangengine/models/paloalto/policy.py
orangengine/models/paloalto/service.py
orangengine/models/paloalto/servicegroup.py
orangengine-0.0.1.dist-info/DESCRIPTION.rst
orangengine-0.0.1.dist-info/METADATA
orangengine-0.0.1.dist-info/RECORD
orangengine-0.0.1.dist-info/WHEEL
orangengine-0.0.1.dist-info/metadata.json
orangengine-0.0.1.dist-info/top_level.txt
