Metadata-Version: 2.0
Name: orangengine
Version: 0.0.1
Summary: Firewall Policy Automation Engine
Home-page: https://github.com/lampwins/orangengine
Author: John Anderson
Author-email: lampwins@gmail.com
License: UNKNOWN
Download-URL: https://github.com/lampwins/orangengine
Platform: UNKNOWN
Requires-Dist: junos-eznc
Requires-Dist: lxml
Requires-Dist: netaddr
Requires-Dist: pandevice
Requires-Dist: terminaltables
